Microsoft-stubs/__init__.pyi
Microsoft-stubs/Win32/__init__.pyi
Microsoft-stubs/Win32/SafeHandles/__init__.pyi
System-stubs/__init__.pyi
System-stubs/Buffers/__init__.pyi
System-stubs/Buffers/Binary/__init__.pyi
System-stubs/Buffers/Text/__init__.pyi
System-stubs/CodeDom/__init__.pyi
System-stubs/CodeDom/Compiler/__init__.pyi
System-stubs/Collections/__init__.pyi
System-stubs/Collections/Concurrent/__init__.pyi
System-stubs/Collections/Generic/__init__.pyi
System-stubs/Collections/ObjectModel/__init__.pyi
System-stubs/Collections/Specialized/__init__.pyi
System-stubs/ComponentModel/__init__.pyi
System-stubs/ComponentModel/Design/__init__.pyi
System-stubs/ComponentModel/Design/Serialization/__init__.pyi
System-stubs/Configuration/__init__.pyi
System-stubs/Configuration/Assemblies/__init__.pyi
System-stubs/Data/__init__.pyi
System-stubs/Data/Common/__init__.pyi
System-stubs/Data/SqlTypes/__init__.pyi
System-stubs/Diagnostics/__init__.pyi
System-stubs/Diagnostics/CodeAnalysis/__init__.pyi
System-stubs/Diagnostics/Contracts/__init__.pyi
System-stubs/Diagnostics/SymbolStore/__init__.pyi
System-stubs/Diagnostics/Tracing/__init__.pyi
System-stubs/Drawing/__init__.pyi
System-stubs/Dynamic/__init__.pyi
System-stubs/Globalization/__init__.pyi
System-stubs/IO/__init__.pyi
System-stubs/IO/Compression/__init__.pyi
System-stubs/IO/Enumeration/__init__.pyi
System-stubs/IO/IsolatedStorage/__init__.pyi
System-stubs/IO/MemoryMappedFiles/__init__.pyi
System-stubs/IO/Pipes/__init__.pyi
System-stubs/Linq/__init__.pyi
System-stubs/Linq/Expressions/__init__.pyi
System-stubs/Linq/Expressions/Interpreter/__init__.pyi
System-stubs/Net/__init__.pyi
System-stubs/Net/Cache/__init__.pyi
System-stubs/Net/Http/__init__.pyi
System-stubs/Net/Http/Headers/__init__.pyi
System-stubs/Net/NetworkInformation/__init__.pyi
System-stubs/Net/Security/__init__.pyi
System-stubs/Net/Sockets/__init__.pyi
System-stubs/Net/WebSockets/__init__.pyi
System-stubs/Numerics/__init__.pyi
netstandard_stubs-2.0.1.dist-info/METADATA
netstandard_stubs-2.0.1.dist-info/WHEEL
netstandard_stubs-2.0.1.dist-info/licenses/LICENSE
netstandard_stubs-2.0.1.dist-info/RECORD
