Metadata-Version: 2.4
Name: netstandard-stubs
Version: 2.0.1
Summary: Unofficial type stubs for .NET Standard
Project-URL: Homepage, https://github.com/Eswcvlad/netstandard-stubs
Project-URL: Issues, https://github.com/Eswcvlad/netstandard-stubs/issues
Author-email: Vlad Lipskiy <eswcvlad@gmail.com>
License-Expression: MIT
License-File: LICENSE
Classifier: Intended Audience :: Developers
Classifier: License :: OSI Approved :: MIT License
Classifier: Operating System :: OS Independent
Classifier: Programming Language :: C#
Classifier: Programming Language :: Python
Classifier: Programming Language :: Python :: 3
Classifier: Programming Language :: Python :: 3 :: Only
Classifier: Programming Language :: Python :: 3.8
Classifier: Programming Language :: Python :: 3.9
Classifier: Programming Language :: Python :: 3.10
Classifier: Programming Language :: Python :: 3.11
Classifier: Programming Language :: Python :: 3.12
Classifier: Programming Language :: Python :: 3.13
Classifier: Programming Language :: Python :: 3.14
Classifier: Typing :: Stubs Only
Requires-Python: >=3.8
